docs/Makefile
docs/changelog.rst
docs/conf.py
docs/create-merged-releases.rst
docs/handle-bad-data.rst
docs/index.rst
docs/requirements.txt
docs/update-merged-releases.rst
docs/api/index.rst
ocdsmerge/__init__.py
ocdsmerge/exceptions.py
ocdsmerge/flatten.py
ocdsmerge/merge.py
ocdsmerge/rules.py
ocdsmerge/util.py
ocdsmerge-0.8.0.dist-info/licenses/LICENSE
ocdsmerge-0.8.0.dist-info/METADATA
ocdsmerge-0.8.0.dist-info/WHEEL
ocdsmerge-0.8.0.dist-info/top_level.txt
ocdsmerge-0.8.0.dist-info/RECORD
