Metadata-Version: 2.4
Name: ocdsmerge
Version: 0.8.0
Summary: A library and reference implementation for merging OCDS releases
Author-email: Open Contracting Partnership <data@open-contracting.org>
License: BSD
Project-URL: Homepage, https://github.com/open-contracting/ocds-merge
Classifier: License :: OSI Approved :: BSD License
Classifier: Operating System :: OS Independent
Classifier: Programming Language :: Python :: 3.9
Classifier: Programming Language :: Python :: 3.10
Classifier: Programming Language :: Python :: 3.11
Classifier: Programming Language :: Python :: 3.12
Classifier: Programming Language :: Python :: Implementation :: CPython
Classifier: Programming Language :: Python :: Implementation :: PyPy
License-File: LICENSE
Requires-Dist: jsonref
Requires-Dist: requests
Provides-Extra: test
Requires-Dist: coverage; extra == "test"
Requires-Dist: jsonschema; extra == "test"
Requires-Dist: pytest; extra == "test"
Dynamic: license-file
